README.txt
setup.py
src/zc/__init__.py
src/zc.thread.egg-info/PKG-INFO
src/zc.thread.egg-info/SOURCES.txt
src/zc.thread.egg-info/dependency_links.txt
src/zc.thread.egg-info/entry_points.txt
src/zc.thread.egg-info/namespace_packages.txt
src/zc.thread.egg-info/not-zip-safe
src/zc.thread.egg-info/requires.txt
src/zc.thread.egg-info/top_level.txt
src/zc/thread/__init__.py
src/zc/thread/tests.py